.travis.yml
AUTHORS
ChangeLog
README.md
requirements.txt
setup.cfg
setup.py
test-requirements.txt
tox.ini
etc/tinytree.ini.sample
tests/__init__.py
tests/etc/unittest.ini
tests/etc/unittest.ini.travis
tests/unit/__init__.py
tests/unit/test_service.py
treestore/__init__.py
treestore/exceptions.py
treestore.egg-info/PKG-INFO
treestore.egg-info/SOURCES.txt
treestore.egg-info/dependency_links.txt
treestore.egg-info/entry_points.txt
treestore.egg-info/not-zip-safe
treestore.egg-info/requires.txt
treestore.egg-info/top_level.txt
treestore/db/__init__.py
treestore/db/api.py
treestore/db/sqltypes.py
treestore/models/__init__.py
treestore/models/base.py
treestore/models/tree_node.py
treestore/models/migration/__init__.py
treestore/models/migration/alembic.ini
treestore/models/migration/cli.py
treestore/models/migration/alembic_migrations/README
treestore/models/migration/alembic_migrations/env.py
treestore/models/migration/alembic_migrations/script.py.mako
treestore/models/migration/alembic_migrations/versions/38c2405af3fb_init.py
treestore/services/__init__.py
treestore/services/node.py