Metadata-Version: 1.1
Name: treestore
Version: 0.1.1
Summary: A tree path indexed key-value store based on L-Tree of PostgreSQL
Home-page: UNKNOWN
Author: Jianing Yang
Author-email: jianingy.yang@gmail.com
License: Apache-2
Platform: UNKNOWN
Classifier: Development Status :: 1 - Planning
Classifier: Environment :: Web Environment
Classifier: Framework :: Flask
Classifier: Intended Audience :: Information Technology
Classifier: License :: OSI Approved :: Apache Software License
Classifier: Operating System :: OS Independent
Classifier: Programming Language :: Python
